mrf_core-1.0.0.dist-info/licenses/LICENSE
mrf_core-1.0.0.dist-info/licenses/NOTICE
mrfcore/__init__.py
mrfcore/diagnostics.py
mrfcore/engine.py
mrfcore/exceptions.py
mrfcore/phases.py
mrfcore/pipeline.py
mrfcore/presets.py
mrfcore/state.py
mrfcore/operators/__init__.py
mrfcore/operators/base.py
mrfcore/operators/evaluate.py
mrfcore/operators/filter.py
mrfcore/operators/inspect.py
mrfcore/operators/reflect.py
mrfcore/operators/rewrite.py
mrfcore/operators/summarize.py
mrfcore/operators/transform.py
mrf_core-1.0.0.dist-info/METADATA
mrf_core-1.0.0.dist-info/WHEEL
mrf_core-1.0.0.dist-info/top_level.txt
mrf_core-1.0.0.dist-info/RECORD
