Metadata-Version: 2.4
Name: mrf-core
Version: 1.0.0
Summary: Modular Reasoning Framework: Multi-stage constraint layer for autonomous agents
Author: Ryan Sabouhi
Author-email: Ryan Sabouhi <rjsabouhi@gmail.com>
License:                                 Apache License
Requires-Python: >=3.9
License-File: LICENSE
License-File: NOTICE
Requires-Dist: numpy>=1.20
Dynamic: license-file
